carto_reader/__init__.py
carto_reader/archive.py
carto_reader/carto_data.py
carto_reader/mesh.py
carto_reader/old.py
carto_reader/points.py
carto_reader/signals.py
carto_reader/utils.py
carto_reader-0.0.12.dist-info/LICENSE
carto_reader-0.0.12.dist-info/METADATA
carto_reader-0.0.12.dist-info/WHEEL
carto_reader-0.0.12.dist-info/top_level.txt
carto_reader-0.0.12.dist-info/RECORD
