Metadata-Version: 2.1
Name: carto-reader
Version: 0.0.12
Summary: Package to read Carto datasets
Author: Josselin Duchateau
Author-email: josselin.duchateau@ihu-liryc.fr
Classifier: Programming Language :: Python :: 3
Classifier: License :: OSI Approved :: GNU General Public License v3 (GPLv3)
Classifier: Operating System :: OS Independent
Requires-Python: >=3.7
License-File: LICENSE
Requires-Dist: numpy
Requires-Dist: tqdm
Requires-Dist: pyvista
Requires-Dist: potpourri3D
